Workbook

Sheet Dashboard
A1: PERSONAL BUDGET TRACKER
A3: BUDGET BREAKDOWN
A4: Income | B4: Tracked | C4: Budget | D4: Remaining
A5: Employment | B5: =SUMIF(Table1[CATEGORY],Dashboard!A5,Table1[AMOUNT]) -> 4000 | C5: ='Budget Category'!B5 -> 4000 | D5: =B5-C5 -> 0
A6: Side Hustle | B6: =SUMIF(Table1[CATEGORY],Dashboard!A6,Table1[AMOUNT]) -> 0 | C6: ='Budget Category'!B6 -> 0 | D6: =B6-C6 -> 0
A7: Passive Income | B7: =SUMIF(Table1[CATEGORY],Dashboard!A7,Table1[AMOUNT]) -> 0 | C7: ='Budget Category'!B7 -> 0 | D7: =B7-C7 -> 0
A8: Total | B8: =SUM(B5:B7) -> 4000 | C8: =SUM(C5:C7) -> 4000 | D8: =SUM(D5:D7) -> 0
A10: Expense | B10: Tracked | C10: Budget | D10: Remaining
A11: Food | B11: =SUMIF(Table1[CATEGORY],Dashboard!A11,Table1[AMOUNT]) -> 742 | C11: ='Budget Category'!B11 -> 700 | D11: =C11-B11 -> -42
A12: Transportation | B12: =SUMIF(Table1[CATEGORY],Dashboard!A12,Table1[AMOUNT]) -> 800 | C12: ='Budget Category'!B12 -> 190 | D12: =C12-B12 -> -610
A13: Car | B13: =SUMIF(Table1[CATEGORY],Dashboard!A13,Table1[AMOUNT]) -> 140 | C13: ='Budget Category'!B13 -> 800 | D13: =C13-B13 -> 660
A14: Dept | B14: =SUMIF(Table1[CATEGORY],Dashboard!A14,Table1[AMOUNT]) -> 820 | C14: ='Budget Category'!B14 -> 350 | D14: =C14-B14 -> -470
A15: Phone Service | B15: =SUMIF(Table1[CATEGORY],Dashboard!A15,Table1[AMOUNT]) -> 200 | C15: ='Budget Category'!B15 -> 60 | D15: =C15-B15 -> -140
A16: Credit | B16: =SUMIF(Table1[CATEGORY],Dashboard!A16,Table1[AMOUNT]) -> 400 | C16: ='Budget Category'!B16 -> 600 | D16: =C16-B16 -> 200
A17: Body Care | B17: =SUMIF(Table1[CATEGORY],Dashboard!A17,Table1[AMOUNT]) -> 150 | C17: ='Budget Category'!B17 -> 150 | D17: =C17-B17 -> 0
A18: Groceries | B18: =SUMIF(Table1[CATEGORY],Dashboard!A18,Table1[AMOUNT]) -> 1000 | C18: ='Budget Category'!B18 -> 800 | D18: =C18-B18 -> -200
A19: Total | B19: =SUM(B11:B18) -> 4252 | C19: =SUM(C11:C18) -> 3650 | D19: =SUM(D11:D18) -> -602
F20: DEBT CALCULATOR DASHBOARD
A21: Savings | B21: Tracked | C21: Budget | D21: Remaining | F21: Results | G21: Current Plan | H21: Cut Spending | I21: Cut + lump sum
A22: Emergency Funds | B22: =C22 -> 250 | C22: ='Budget Category'!B22 -> 250 | D22: =C22-B22 -> 0 | F22: Starting Balance | G22: ='Dept Calculator'!B5 -> 57900 | H22: ='Dept Calculator'!B5 -> 57900 | I22: =MAX('Dept Calculator'!B5-'Dept Calculator'!B9,0) -> 55900
A23: Investment | B23: =C23 -> 100 | C23: ='Budget Category'!B23 -> 100 | D23: =C23-B23 -> 0 | F23: Monthly payment | G23: ='Dept Calculator'!B7 -> 1040 | H23: ='Dept Calculator'!B7+'Budget Category'!E19 -> 1244 | I23: =H23 -> 1244
A24: Extra Savings | B24: =C24 -> 0 | C24: ='Budget Category'!B24 -> 0 | D24: =C24-B24 -> 0 | F24: Monthly interest rate | G24: ='Dept Calculator'!$B$6/12 -> 0.006575 | H24: ='Dept Calculator'!$B$6/12 -> 0.006575 | I24: ='Dept Calculator'!$B$6/12 -> 0.006575
A25: Total | B25: =SUM(B22:B24) -> 350 | C25: =SUM(C22:C24) -> 350 | D25: =SUM(D22:D24) -> 0 | F25: Months to pay off (exact) | G25: =IF(G22<=0,0,IF(G23<=G22*G24,"Payment too low",NPER(G24,-G23,G22))) -> 69.548701 | H25: =IF(H22<=0,0,IF(H23<=H22*H24,"Payment too low",NPER(H24,-H23,H22))) -> 55.743878 | I25: =IF(I22<=0,0,IF(I23<=I22*I24,"Payment too low",NPER(I24,-I23,I22))) -> 53.437122
F26: Months (round up) | G26: =IF(ISNUMBER(G25),ROUNDUP(G25,0),"N/A") -> 70 | H26: =IF(ISNUMBER(H25),ROUNDUP(H25,0),"N/A") -> 56 | I26: =IF(ISNUMBER(I25),ROUNDUP(I25,0),"N/A") -> 54
A27: TOTAL | B27: =B8-B19-B25 -> -602 | F27: Time to debt-free | G27: =IF(ISNUMBER(G26),INT(G26/12)&" yr "&MOD(G26,12)&" mo","n/a") -> 5 yr 10 mo | H27: =IF(ISNUMBER(H26),INT(H26/12)&" yr "&MOD(H26,12)&" mo","n/a") -> 4 yr 8 mo | I27: =IF(ISNUMBER(I26),INT(I26/12)&" yr "&MOD(I26,12)&" mo","n/a") -> 4 yr 6 mo
F28: Estimated payoff date | G28: =IF(ISNUMBER(G26),EDATE(TODAY(),G26),"n/a") -> 48423 | H28: =IF(ISNUMBER(H26),EDATE(TODAY(),H26),"n/a") -> 47996 | I28: =IF(ISNUMBER(I26),EDATE(TODAY(),I26),"n/a") -> 47935
F29: Total interest paid | G29: =IF(ISNUMBER(G25),G23*G25-G22,"n/a") -> 14430.649 | H29: =IF(ISNUMBER(H25),H23*H25-H22,"n/a") -> 11445.384 | I29: =IF(ISNUMBER(I25),I23*I25-I22,"n/a") -> 10575.78
F30: Interest saved vs current plan | G30: - | H30: =IF(AND(ISNUMBER($G$29),ISNUMBER(H29)),$G$29-H29,"n/a") -> 2985.2653 | I30: =IF(AND(ISNUMBER($G$29),ISNUMBER(I29)),$G$29-I29,"n/a") -> 3854.8688
F31: Months saved vs current plan | G31: - | H31: =IF(AND(ISNUMBER($G$26),ISNUMBER(H26)),$G$26-H26,"n/a") -> 14 | I31: =IF(AND(ISNUMBER($G$26),ISNUMBER(I26)),$G$26-I26,"n/a") -> 16
A97: Income | B97: Expense
A98: =B8 -> 4000 | B98: =B19+B25 -> 4602
A100: Sum of Income | B100: Sum of Expense
A101: 4000 | B101: 4602

Sheet Budget Category
A1: BUDGET CATEGORY | K1: EXPENSE INPUT TRACKER
K3: DATE | L3: Type | M3: CATEGORY | N3: AMOUNT
A4: Income | B4: Monthly ($) | K4: 46267 | L4: Expense | M4: Body Care | N4: 150
A5: Employment | B5: 4000 | K5: 46268 | L5: Expense | M5: Phone Service | N5: 200
A6: Side Hustle | B6: 0 | K6: 46269 | L6: Expense | M6: Car | N6: 140
A7: Passive Income | B7: 0 | K7: 46270 | L7: Expense | M7: Transportation | N7: 500
A8: Total | B8: =SUM(B5:B7) -> 4000 | K8: 46271 | L8: Expense | M8: Transportation | N8: 300
K9: 46272 | L9: Expense | M9: Dept | N9: 380
A10: Expense | B10: Monthly ($) | C10: Cuttable? (Y/N) | D10: After cut ($) | E10: Freed up ($) | K10: 46273 | L10: Expense | M10: Food | N10: 42
A11: Food | B11: 700 | C11: Y | D11: =IF(C11="Y",B11*(1-'Dept Calculator'!$B$8),B11) -> 630 | E11: =B11-D11 -> 70 | K11: 46274 | L11: Expense | M11: Dept | N11: 440
A12: Transportation | B12: 190 | C12: Y | D12: =IF(C12="Y",B12*(1-'Dept Calculator'!$B$8),B12) -> 171 | E12: =B12-D12 -> 19 | K12: 46275 | L12: Expense | M12: Food | N12: 300
A13: Car | B13: 800 | C13: Y | D13: =IF(C13="Y",B13*(1-'Dept Calculator'!$B$8),B13) -> 720 | E13: =B13-D13 -> 80 | K13: 46276 | L13: Expense | M13: Food | N13: 300
A14: Dept | B14: 350 | C14: Y | D14: =IF(C14="Y",B14*(1-'Dept Calculator'!$B$8),B14) -> 315 | E14: =B14-D14 -> 35 | K14: 46277 | L14: Expense | M14: Food | N14: 100
A15: Phone Service | B15: 60 | C15: N | D15: =IF(C15="Y",B15*(1-'Dept Calculator'!$B$8),B15) -> 60 | E15: =B15-D15 -> 0 | K15: 46278 | L15: Income | M15: Employment | N15: 4000
A16: Credit | B16: 600 | C16: N | D16: =IF(C16="Y",B16*(1-'Dept Calculator'!$B$8),B16) -> 600 | E16: =B16-D16 -> 0 | K16: 46279 | L16: Income | M16: Side Hustle
A17: Body Care | B17: 150 | C17: N | D17: =IF(C17="Y",B17*(1-'Dept Calculator'!$B$8),B17) -> 150 | E17: =B17-D17 -> 0 | K17: 46280 | L17: Expense | M17: Credit | N17: 400
A18: Groceries | B18: 800 | C18: N | D18: =IF(C18="Y",B18*(1-'Dept Calculator'!$B$8),B18) -> 800 | E18: =B18-D18 -> 0 | K18: 46281 | L18: Expense | M18: Groceries | N18: 1000
A19: Total | B19: =SUM(B11:B18) -> 3650 | D19: =SUM(D11:D18) -> 3446 | E19: =SUM(E11:E18) -> 204 | K19: 46282
A21: Savings | B21: Monthly ($)
A22: Emergency Funds | B22: 250
A23: Investment | B23: 100
A24: Extra Savings | B24: 0
A25: Total | B25: =SUM(B22:B24) -> 350
B27: NOT ALLOTED
B28: MONTH
B29: =B8-B19-B25 -> 0

Sheet Dept Calculator
A1: Dept Payoff Calculator
A4: INPUTS
A5: Debt Balance | B5: 57900
A6: Interest Rate | B6: 0.0789
A7: Current Monthly Payment | B7: 1040
A8: Spending Cut % | B8: 0.1
A9: Lump Sum From Savings (Optional) | B9: 2000
